ptb_pagination/__init__.py
ptb_pagination/pagination.py
ptb_pagination-0.0.5.dist-info/licenses/LICENSE
ptb_pagination-0.0.5.dist-info/METADATA
ptb_pagination-0.0.5.dist-info/WHEEL
ptb_pagination-0.0.5.dist-info/top_level.txt
ptb_pagination-0.0.5.dist-info/RECORD
