Metadata-Version: 2.4
Name: ptb-pagination
Version: 0.0.5
Summary: Python inline keyboard pagination for Telegram Bot API.
Home-page: https://github.com/wiltonsr/ptb-pagination
Author: Wilton Rodrigues
Author-email: wiltonsr94@gmail.com
License: MIT
Platform: any
License-File: LICENSE
Requires-Dist: python-telegram-bot[callback-data]>=13.6
Dynamic: author
Dynamic: author-email
Dynamic: description
Dynamic: description-content-type
Dynamic: home-page
Dynamic: license
Dynamic: license-file
Dynamic: platform
Dynamic: requires-dist
Dynamic: summary
